qv_rag/__init__.py
qv_rag/engine.py
qv_rag/storage.py
qv_rag/text_splitter.py
qv_rag-0.1.0.dist-info/METADATA
qv_rag-0.1.0.dist-info/WHEEL
qv_rag-0.1.0.dist-info/licenses/LICENSE
qv_rag-0.1.0.dist-info/RECORD
