Metadata-Version: 2.4
Name: qv-rag
Version: 0.1.0
Summary: A lightweight, modular RAG system using ChromaDB
License-File: LICENSE
Requires-Python: >=3.12
Requires-Dist: bs4>=0.0.2
Requires-Dist: chromadb>=1.0.5
Requires-Dist: langchain-community>=0.3.21
Requires-Dist: langchain-text-splitters>=0.3.8
Requires-Dist: pytest>=8.3.5
Requires-Dist: sentence-transformers>=4.1.0
